{
  "uid": "onefintech-member-lifecycle",
  "title": "Member Lifecycle",
  "tags": [
    "onefintech",
    "members"
  ],
  "timezone": "browser",
  "time": {
    "from": "now-90d",
    "to": "now"
  },
  "timepicker": {},
  "refresh": "1m",
  "schemaVersion": 39,
  "version": 1,
  "panels": [
    {
      "id": 60,
      "type": "stat",
      "title": "Members",
      "gridPos": {
        "h": 4,
        "w": 6,
        "x": 0,
        "y": 0
      },
      "datasource": {
        "type": "grafana-postgresql-datasource",
        "uid": "cfglj9j8ghwqob"
      },
      "targets": [
        {
          "datasource": {
            "type": "grafana-postgresql-datasource",
            "uid": "cfglj9j8ghwqob"
          },
          "format": "table",
          "rawQuery": true,
          "rawSql": "\nSELECT COUNT(DISTINCT client_member_id) FROM consumers\nWHERE client_member_id LIKE CASE WHEN '${medicaid_id}' = '' THEN '%' ELSE '${medicaid_id}' END\n",
          "refId": "A"
        }
      ],
      "options": {
        "colorMode": "background",
        "graphMode": "none",
        "justifyMode": "center",
        "orientation": "auto",
        "reduceOptions": {
          "calcs": [
            "lastNotNull"
          ],
          "fields": "",
          "values": false
        },
        "textMode": "auto"
      },
      "fieldConfig": {
        "defaults": {
          "unit": "short",
          "thresholds": {
            "mode": "absolute",
            "steps": [
              {
                "color": "blue",
                "value": null
              }
            ]
          },
          "color": {
            "mode": "thresholds"
          },
          "mappings": []
        },
        "overrides": []
      },
      "pluginVersion": "10.4.3"
    },
    {
      "id": 61,
      "type": "stat",
      "title": "Active Purses",
      "gridPos": {
        "h": 4,
        "w": 6,
        "x": 6,
        "y": 0
      },
      "datasource": {
        "type": "grafana-postgresql-datasource",
        "uid": "cfglj9j8ghwqob"
      },
      "targets": [
        {
          "datasource": {
            "type": "grafana-postgresql-datasource",
            "uid": "cfglj9j8ghwqob"
          },
          "format": "table",
          "rawQuery": true,
          "rawSql": "\nSELECT COUNT(*) FROM purses p\nJOIN consumers c ON c.id = p.consumer_id\nWHERE p.status = 'ACTIVE'\n  AND c.client_member_id LIKE CASE WHEN '${medicaid_id}' = '' THEN '%' ELSE '${medicaid_id}' END\n",
          "refId": "A"
        }
      ],
      "options": {
        "colorMode": "background",
        "graphMode": "none",
        "justifyMode": "center",
        "orientation": "auto",
        "reduceOptions": {
          "calcs": [
            "lastNotNull"
          ],
          "fields": "",
          "values": false
        },
        "textMode": "auto"
      },
      "fieldConfig": {
        "defaults": {
          "unit": "short",
          "thresholds": {
            "mode": "absolute",
            "steps": [
              {
                "color": "blue",
                "value": null
              }
            ]
          },
          "color": {
            "mode": "thresholds"
          },
          "mappings": []
        },
        "overrides": []
      },
      "pluginVersion": "10.4.3"
    },
    {
      "id": 62,
      "type": "stat",
      "title": "Active Balance ($)",
      "gridPos": {
        "h": 4,
        "w": 6,
        "x": 12,
        "y": 0
      },
      "datasource": {
        "type": "grafana-postgresql-datasource",
        "uid": "cfglj9j8ghwqob"
      },
      "targets": [
        {
          "datasource": {
            "type": "grafana-postgresql-datasource",
            "uid": "cfglj9j8ghwqob"
          },
          "format": "table",
          "rawQuery": true,
          "rawSql": "\nSELECT ROUND(SUM(p.available_balance_cents) / 100.0, 2)\nFROM purses p\nJOIN consumers c ON c.id = p.consumer_id\nWHERE p.status = 'ACTIVE'\n  AND c.client_member_id LIKE CASE WHEN '${medicaid_id}' = '' THEN '%' ELSE '${medicaid_id}' END\n",
          "refId": "A"
        }
      ],
      "options": {
        "colorMode": "background",
        "graphMode": "none",
        "justifyMode": "center",
        "orientation": "auto",
        "reduceOptions": {
          "calcs": [
            "lastNotNull"
          ],
          "fields": "",
          "values": false
        },
        "textMode": "auto"
      },
      "fieldConfig": {
        "defaults": {
          "unit": "currencyUSD",
          "thresholds": {
            "mode": "absolute",
            "steps": [
              {
                "color": "blue",
                "value": null
              }
            ]
          },
          "color": {
            "mode": "thresholds"
          },
          "mappings": []
        },
        "overrides": []
      },
      "pluginVersion": "10.4.3"
    },
    {
      "id": 63,
      "type": "stat",
      "title": "Benefit Periods",
      "gridPos": {
        "h": 4,
        "w": 6,
        "x": 18,
        "y": 0
      },
      "datasource": {
        "type": "grafana-postgresql-datasource",
        "uid": "cfglj9j8ghwqob"
      },
      "targets": [
        {
          "datasource": {
            "type": "grafana-postgresql-datasource",
            "uid": "cfglj9j8ghwqob"
          },
          "format": "table",
          "rawQuery": true,
          "rawSql": "\nSELECT COUNT(DISTINCT p.benefit_period)\nFROM purses p\nJOIN consumers c ON c.id = p.consumer_id\nWHERE c.client_member_id LIKE CASE WHEN '${medicaid_id}' = '' THEN '%' ELSE '${medicaid_id}' END\n",
          "refId": "A"
        }
      ],
      "options": {
        "colorMode": "background",
        "graphMode": "none",
        "justifyMode": "center",
        "orientation": "auto",
        "reduceOptions": {
          "calcs": [
            "lastNotNull"
          ],
          "fields": "",
          "values": false
        },
        "textMode": "auto"
      },
      "fieldConfig": {
        "defaults": {
          "unit": "short",
          "thresholds": {
            "mode": "absolute",
            "steps": [
              {
                "color": "blue",
                "value": null
              }
            ]
          },
          "color": {
            "mode": "thresholds"
          },
          "mappings": []
        },
        "overrides": []
      },
      "pluginVersion": "10.4.3"
    },
    {
      "id": 64,
      "type": "table",
      "title": "Member lifecycle \u2014 all files, all periods",
      "gridPos": {
        "h": 16,
        "w": 24,
        "x": 0,
        "y": 4
      },
      "datasource": {
        "type": "grafana-postgresql-datasource",
        "uid": "cfglj9j8ghwqob"
      },
      "targets": [
        {
          "datasource": {
            "type": "grafana-postgresql-datasource",
            "uid": "cfglj9j8ghwqob"
          },
          "format": "table",
          "rawQuery": true,
          "rawSql": "\nSELECT\n  c.client_member_id                                            AS \"Member ID\",\n  c.last_name || ', ' || c.first_name                           AS \"Name\",\n  c.status                                                      AS \"Consumer Status\",\n  ca.pan_masked                                                 AS \"Card (masked)\",\n  ca.card_status                                                AS \"Card Status\",\n  p.benefit_period                                              AS \"Period\",\n  p.benefit_type                                                AS \"Benefit Type\",\n  p.purse_type                                                  AS \"Purse Type\",\n  p.status                                                      AS \"Purse Status\",\n  ROUND(p.available_balance_cents / 100.0, 2)                   AS \"Balance ($)\",\n  p.effective_date                                              AS \"Effective\",\n  p.expiry_date                                                 AS \"Expires\",\n  -- ENROLL command outcome\n  CASE\n    WHEN dc_enroll.status = 'Completed' THEN '\u2705 enrolled'\n    WHEN dc_enroll.status = 'Failed'    THEN '\u274c failed'\n    WHEN dc_enroll.status = 'Duplicate' THEN '\u26a0\ufe0f duplicate'\n    WHEN dc_enroll.status IS NOT NULL   THEN '\u23f3 ' || dc_enroll.status\n    ELSE '\u2014'\n  END                                                           AS \"Enroll Cmd\",\n  -- RT30 card issuance\n  CASE\n    WHEN rt30.completed_at IS NOT NULL\n     AND (rt30.fis_result_code IS NULL OR rt30.fis_result_code IN ('','00'))\n     THEN '\u2705 issued'\n    WHEN rt30.completed_at IS NOT NULL\n     THEN '\u274c ' || COALESCE(rt30.fis_result_code,'err')\n    WHEN rt30.submitted_at IS NOT NULL THEN '\u23f3 submitted'\n    WHEN rt30.id IS NOT NULL           THEN '\u23f3 staged'\n    ELSE '\u2014'\n  END                                                           AS \"Card Issued\",\n  -- RT60 purse load for this period\n  CASE\n    WHEN rt60.completed_at IS NOT NULL\n     AND (rt60.fis_result_code IS NULL OR rt60.fis_result_code IN ('','00'))\n     THEN '\u2705 loaded'\n    WHEN rt60.completed_at IS NOT NULL\n     THEN '\u274c ' || COALESCE(rt60.fis_result_code,'err')\n    WHEN rt60.submitted_at IS NOT NULL THEN '\u23f3 submitted'\n    WHEN rt60.id IS NOT NULL           THEN '\u23f3 staged'\n    ELSE '\u2014'\n  END                                                           AS \"Benefit Loaded\",\n  -- Source file for this period's load\n  TO_CHAR(bf_load.arrived_at AT TIME ZONE 'UTC', 'YYYY-MM-DD HH24:MI')\n    || ' \u00b7 ' || bf_load.file_type                               AS \"Source File\",\n  bf_load.correlation_id                                        AS \"Correlation ID\"\nFROM consumers c\nJOIN cards ca\n  ON ca.consumer_id = c.id\nLEFT JOIN purses p\n  ON p.consumer_id = c.id\nLEFT JOIN batch_files bf_load\n  ON bf_load.id = p.source_batch_file_id\nLEFT JOIN domain_commands dc_enroll\n  ON dc_enroll.tenant_id = c.tenant_id\n AND dc_enroll.client_member_id = c.client_member_id\n AND dc_enroll.command_type = 'ENROLL'\nLEFT JOIN batch_records_rt30 rt30\n  ON rt30.client_member_id = c.client_member_id\n AND rt30.tenant_id = c.tenant_id\nLEFT JOIN batch_records_rt60 rt60\n  ON rt60.client_member_id = c.client_member_id\n AND rt60.tenant_id = c.tenant_id\n AND rt60.effective_date = p.effective_date\nWHERE c.client_member_id LIKE CASE WHEN '${medicaid_id}' = '' THEN '%' ELSE '${medicaid_id}' END\nORDER BY c.client_member_id, p.benefit_period DESC, p.benefit_type\nLIMIT 1000\n",
          "refId": "A"
        }
      ],
      "options": {
        "sortBy": [],
        "footer": {
          "show": false
        }
      },
      "fieldConfig": {
        "defaults": {
          "custom": {
            "align": "auto",
            "displayMode": "auto",
            "filterable": true,
            "inspect": false
          },
          "mappings": [],
          "thresholds": {
            "mode": "absolute",
            "steps": [
              {
                "color": "green",
                "value": null
              }
            ]
          }
        },
        "overrides": [
          {
            "matcher": {
              "id": "byName",
              "options": "Consumer Status"
            },
            "properties": [
              {
                "id": "custom.displayMode",
                "value": "color-background"
              },
              {
                "id": "thresholds",
                "value": {
                  "mode": "absolute",
                  "steps": [
                    {
                      "color": "green",
                      "value": null
                    }
                  ]
                }
              },
              {
                "id": "mappings",
                "value": [
                  {
                    "type": "value",
                    "options": {
                      "COMPLETE": {
                        "color": "green",
                        "index": 0,
                        "text": "COMPLETE"
                      },
                      "PROCESSING": {
                        "color": "blue",
                        "index": 1,
                        "text": "PROCESSING"
                      },
                      "SUBMITTED": {
                        "color": "blue",
                        "index": 2,
                        "text": "SUBMITTED"
                      },
                      "ASSEMBLED": {
                        "color": "blue",
                        "index": 3,
                        "text": "ASSEMBLED"
                      },
                      "VALIDATING": {
                        "color": "yellow",
                        "index": 4,
                        "text": "VALIDATING"
                      },
                      "RECEIVED": {
                        "color": "yellow",
                        "index": 5,
                        "text": "RECEIVED"
                      },
                      "STALLED": {
                        "color": "orange",
                        "index": 6,
                        "text": "STALLED"
                      },
                      "HALTED": {
                        "color": "red",
                        "index": 7,
                        "text": "HALTED"
                      },
                      "FAILED": {
                        "color": "red",
                        "index": 8,
                        "text": "FAILED"
                      },
                      "enrolled": {
                        "color": "green",
                        "index": 9,
                        "text": "enrolled"
                      },
                      "failed": {
                        "color": "red",
                        "index": 10,
                        "text": "failed"
                      },
                      "staged": {
                        "color": "yellow",
                        "index": 11,
                        "text": "staged"
                      },
                      "STAGED": {
                        "color": "yellow",
                        "index": 12,
                        "text": "STAGED"
                      },
                      "COMPLETED": {
                        "color": "green",
                        "index": 13,
                        "text": "COMPLETED"
                      },
                      "Completed": {
                        "color": "green",
                        "index": 14,
                        "text": "Completed"
                      },
                      "Failed": {
                        "color": "red",
                        "index": 15,
                        "text": "Failed"
                      },
                      "Accepted": {
                        "color": "blue",
                        "index": 16,
                        "text": "Accepted"
                      },
                      "Duplicate": {
                        "color": "orange",
                        "index": 17,
                        "text": "Duplicate"
                      },
                      "ACTIVE": {
                        "color": "green",
                        "index": 18,
                        "text": "ACTIVE"
                      },
                      "PENDING": {
                        "color": "yellow",
                        "index": 19,
                        "text": "PENDING"
                      },
                      "SUSPENDED": {
                        "color": "orange",
                        "index": 20,
                        "text": "SUSPENDED"
                      },
                      "TERMINATED": {
                        "color": "red",
                        "index": 21,
                        "text": "TERMINATED"
                      }
                    }
                  }
                ]
              }
            ]
          },
          {
            "matcher": {
              "id": "byName",
              "options": "Card Status"
            },
            "properties": [
              {
                "id": "custom.displayMode",
                "value": "color-background"
              },
              {
                "id": "thresholds",
                "value": {
                  "mode": "absolute",
                  "steps": [
                    {
                      "color": "green",
                      "value": null
                    }
                  ]
                }
              },
              {
                "id": "mappings",
                "value": [
                  {
                    "type": "value",
                    "options": {
                      "COMPLETE": {
                        "color": "green",
                        "index": 0,
                        "text": "COMPLETE"
                      },
                      "PROCESSING": {
                        "color": "blue",
                        "index": 1,
                        "text": "PROCESSING"
                      },
                      "SUBMITTED": {
                        "color": "blue",
                        "index": 2,
                        "text": "SUBMITTED"
                      },
                      "ASSEMBLED": {
                        "color": "blue",
                        "index": 3,
                        "text": "ASSEMBLED"
                      },
                      "VALIDATING": {
                        "color": "yellow",
                        "index": 4,
                        "text": "VALIDATING"
                      },
                      "RECEIVED": {
                        "color": "yellow",
                        "index": 5,
                        "text": "RECEIVED"
                      },
                      "STALLED": {
                        "color": "orange",
                        "index": 6,
                        "text": "STALLED"
                      },
                      "HALTED": {
                        "color": "red",
                        "index": 7,
                        "text": "HALTED"
                      },
                      "FAILED": {
                        "color": "red",
                        "index": 8,
                        "text": "FAILED"
                      },
                      "enrolled": {
                        "color": "green",
                        "index": 9,
                        "text": "enrolled"
                      },
                      "failed": {
                        "color": "red",
                        "index": 10,
                        "text": "failed"
                      },
                      "staged": {
                        "color": "yellow",
                        "index": 11,
                        "text": "staged"
                      },
                      "STAGED": {
                        "color": "yellow",
                        "index": 12,
                        "text": "STAGED"
                      },
                      "COMPLETED": {
                        "color": "green",
                        "index": 13,
                        "text": "COMPLETED"
                      },
                      "Completed": {
                        "color": "green",
                        "index": 14,
                        "text": "Completed"
                      },
                      "Failed": {
                        "color": "red",
                        "index": 15,
                        "text": "Failed"
                      },
                      "Accepted": {
                        "color": "blue",
                        "index": 16,
                        "text": "Accepted"
                      },
                      "Duplicate": {
                        "color": "orange",
                        "index": 17,
                        "text": "Duplicate"
                      },
                      "ACTIVE": {
                        "color": "green",
                        "index": 18,
                        "text": "ACTIVE"
                      },
                      "PENDING": {
                        "color": "yellow",
                        "index": 19,
                        "text": "PENDING"
                      },
                      "SUSPENDED": {
                        "color": "orange",
                        "index": 20,
                        "text": "SUSPENDED"
                      },
                      "TERMINATED": {
                        "color": "red",
                        "index": 21,
                        "text": "TERMINATED"
                      }
                    }
                  }
                ]
              }
            ]
          },
          {
            "matcher": {
              "id": "byName",
              "options": "Purse Status"
            },
            "properties": [
              {
                "id": "custom.displayMode",
                "value": "color-background"
              },
              {
                "id": "thresholds",
                "value": {
                  "mode": "absolute",
                  "steps": [
                    {
                      "color": "green",
                      "value": null
                    }
                  ]
                }
              },
              {
                "id": "mappings",
                "value": [
                  {
                    "type": "value",
                    "options": {
                      "COMPLETE": {
                        "color": "green",
                        "index": 0,
                        "text": "COMPLETE"
                      },
                      "PROCESSING": {
                        "color": "blue",
                        "index": 1,
                        "text": "PROCESSING"
                      },
                      "SUBMITTED": {
                        "color": "blue",
                        "index": 2,
                        "text": "SUBMITTED"
                      },
                      "ASSEMBLED": {
                        "color": "blue",
                        "index": 3,
                        "text": "ASSEMBLED"
                      },
                      "VALIDATING": {
                        "color": "yellow",
                        "index": 4,
                        "text": "VALIDATING"
                      },
                      "RECEIVED": {
                        "color": "yellow",
                        "index": 5,
                        "text": "RECEIVED"
                      },
                      "STALLED": {
                        "color": "orange",
                        "index": 6,
                        "text": "STALLED"
                      },
                      "HALTED": {
                        "color": "red",
                        "index": 7,
                        "text": "HALTED"
                      },
                      "FAILED": {
                        "color": "red",
                        "index": 8,
                        "text": "FAILED"
                      },
                      "enrolled": {
                        "color": "green",
                        "index": 9,
                        "text": "enrolled"
                      },
                      "failed": {
                        "color": "red",
                        "index": 10,
                        "text": "failed"
                      },
                      "staged": {
                        "color": "yellow",
                        "index": 11,
                        "text": "staged"
                      },
                      "STAGED": {
                        "color": "yellow",
                        "index": 12,
                        "text": "STAGED"
                      },
                      "COMPLETED": {
                        "color": "green",
                        "index": 13,
                        "text": "COMPLETED"
                      },
                      "Completed": {
                        "color": "green",
                        "index": 14,
                        "text": "Completed"
                      },
                      "Failed": {
                        "color": "red",
                        "index": 15,
                        "text": "Failed"
                      },
                      "Accepted": {
                        "color": "blue",
                        "index": 16,
                        "text": "Accepted"
                      },
                      "Duplicate": {
                        "color": "orange",
                        "index": 17,
                        "text": "Duplicate"
                      },
                      "ACTIVE": {
                        "color": "green",
                        "index": 18,
                        "text": "ACTIVE"
                      },
                      "PENDING": {
                        "color": "yellow",
                        "index": 19,
                        "text": "PENDING"
                      },
                      "SUSPENDED": {
                        "color": "orange",
                        "index": 20,
                        "text": "SUSPENDED"
                      },
                      "TERMINATED": {
                        "color": "red",
                        "index": 21,
                        "text": "TERMINATED"
                      }
                    }
                  }
                ]
              }
            ]
          },
          {
            "matcher": {
              "id": "byName",
              "options": "Enroll Cmd"
            },
            "properties": [
              {
                "id": "custom.displayMode",
                "value": "color-background"
              },
              {
                "id": "mappings",
                "value": [
                  {
                    "type": "value",
                    "options": {
                      "\u2705 enrolled": {
                        "color": "green",
                        "index": 0
                      },
                      "\u274c failed": {
                        "color": "red",
                        "index": 1
                      },
                      "\u26a0\ufe0f duplicate": {
                        "color": "orange",
                        "index": 2
                      }
                    }
                  }
                ]
              }
            ]
          },
          {
            "matcher": {
              "id": "byName",
              "options": "Card Issued"
            },
            "properties": [
              {
                "id": "custom.displayMode",
                "value": "color-background"
              },
              {
                "id": "mappings",
                "value": [
                  {
                    "type": "value",
                    "options": {
                      "\u2705 issued": {
                        "color": "green",
                        "index": 0
                      },
                      "\u23f3 submitted": {
                        "color": "blue",
                        "index": 1
                      },
                      "\u23f3 staged": {
                        "color": "yellow",
                        "index": 2
                      },
                      "\u2014": {
                        "color": "super-light-gray",
                        "index": 3
                      }
                    }
                  }
                ]
              }
            ]
          },
          {
            "matcher": {
              "id": "byName",
              "options": "Benefit Loaded"
            },
            "properties": [
              {
                "id": "custom.displayMode",
                "value": "color-background"
              },
              {
                "id": "mappings",
                "value": [
                  {
                    "type": "value",
                    "options": {
                      "\u2705 loaded": {
                        "color": "green",
                        "index": 0
                      },
                      "\u23f3 submitted": {
                        "color": "blue",
                        "index": 1
                      },
                      "\u23f3 staged": {
                        "color": "yellow",
                        "index": 2
                      },
                      "\u2014": {
                        "color": "super-light-gray",
                        "index": 3
                      }
                    }
                  }
                ]
              }
            ]
          },
          {
            "matcher": {
              "id": "byName",
              "options": "Source File"
            },
            "properties": [
              {
                "id": "links",
                "value": [
                  {
                    "title": "Open file detail",
                    "url": "/d/onefintech-file-detail/file-detail?var-fileId=${__data.fields['Correlation ID']}",
                    "targetBlank": false
                  }
                ]
              }
            ]
          },
          {
            "matcher": {
              "id": "byName",
              "options": "Correlation ID"
            },
            "properties": [
              {
                "id": "custom.hidden",
                "value": true
              }
            ]
          }
        ]
      },
      "pluginVersion": "10.4.3"
    }
  ],
  "templating": {
    "list": [
      {
        "hide": 0,
        "label": "Medicaid ID",
        "name": "medicaid_id",
        "query": "",
        "skipUrlSync": false,
        "type": "textbox",
        "current": {
          "value": ""
        }
      }
    ]
  },
  "annotations": {
    "list": []
  },
  "links": [
    {
      "title": "Ops Health",
      "url": "/d/onefintech-ops-health/ops-health",
      "type": "link",
      "icon": "external link",
      "tags": [],
      "asDropdown": false,
      "includeVars": false,
      "keepTime": true,
      "targetBlank": false
    },
    {
      "title": "File Detail",
      "url": "/d/onefintech-file-detail/file-detail",
      "type": "link",
      "icon": "external link",
      "tags": [],
      "asDropdown": false,
      "includeVars": false,
      "keepTime": true,
      "targetBlank": false
    },
    {
      "title": "Member Lifecycle",
      "url": "/d/onefintech-member-lifecycle/member-lifecycle",
      "type": "link",
      "icon": "external link",
      "tags": [],
      "asDropdown": false,
      "includeVars": false,
      "keepTime": true,
      "targetBlank": false
    },
    {
      "title": "UAT Validation",
      "url": "/d/onefintech-uat-v2/uat-validation",
      "type": "link",
      "icon": "external link",
      "tags": [],
      "asDropdown": false,
      "includeVars": false,
      "keepTime": true,
      "targetBlank": false
    },
    {
      "title": "Platform Config",
      "url": "/d/onefintech-platform-config/platform-config",
      "type": "link",
      "icon": "external link",
      "tags": [],
      "asDropdown": false,
      "includeVars": false,
      "keepTime": true,
      "targetBlank": false
    },
    {
      "title": "Tests",
      "url": "/d/onefintech-tests/test-runs",
      "type": "link",
      "icon": "external link",
      "tags": [],
      "asDropdown": false,
      "includeVars": false,
      "keepTime": true,
      "targetBlank": false
    }
  ]
}